abstract_tracker/__init__.py
abstract_tracker/_version.py
abstract_tracker/api.py
abstract_tracker/base.py
abstract_tracker/exc.py
abstract_tracker/logger.py
abstract_tracker/paths.py
abstract_tracker/docs/__init__.py
abstract_tracker/tests/__init__.py
abstract_tracker/tests/helper.py
abstract_tracker/tests/mock_aws.py
abstract_tracker/tests/task.py
abstract_tracker/trackers/__init__.py
abstract_tracker/trackers/file_tracker.py
abstract_tracker/trackers/s3_tracker.py
abstract_tracker/vendor/__init__.py
abstract_tracker/vendor/better_enum.py
abstract_tracker/vendor/nested_logger.py
abstract_tracker/vendor/pytest_cov_helper.py
abstract_tracker-0.1.1.dist-info/AUTHORS.rst
abstract_tracker-0.1.1.dist-info/LICENSE.txt
abstract_tracker-0.1.1.dist-info/METADATA
abstract_tracker-0.1.1.dist-info/WHEEL
abstract_tracker-0.1.1.dist-info/top_level.txt
abstract_tracker-0.1.1.dist-info/RECORD
