Metadata-Version: 2.1
Name: abstract_tracker
Version: 0.1.1
Summary: Library for creating status tracking library.
Home-page: https://github.com/MacHu-GWU/abstract_tracker-project
Download-URL: https://pypi.python.org/pypi/abstract_tracker/0.1.1#downloads
Author: Sanhe Hu
Author-email: husanhe@gmail.com
Maintainer: Sanhe Hu
Maintainer-email: husanhe@gmail.com
License: MIT
Platform: Windows
Platform: MacOS
Platform: Unix
Classifier: Development Status :: 4 - Beta
Classifier: Intended Audience :: Developers
Classifier: License :: OSI Approved :: MIT License
Classifier: Natural Language :: English
Classifier: Operating System :: Microsoft :: Windows
Classifier: Operating System :: MacOS
Classifier: Operating System :: Unix
Classifier: Programming Language :: Python
Classifier: Programming Language :: Python :: 3.7
Classifier: Programming Language :: Python :: 3.8
Classifier: Programming Language :: Python :: 3.9
Classifier: Programming Language :: Python :: 3.10
Classifier: Programming Language :: Python :: 3.11
Classifier: Programming Language :: Python :: 3.12
Classifier: Programming Language :: Python :: 3 :: Only
Requires-Python: >=3.7
License-File: LICENSE.txt
License-File: AUTHORS.rst
Provides-Extra: docs
Requires-Dist: Sphinx ==5.3.0 ; extra == 'docs'
Requires-Dist: sphinx-jinja ==2.0.2 ; extra == 'docs'
Requires-Dist: sphinx-copybutton ==0.5.1 ; extra == 'docs'
Requires-Dist: sphinx-design ==0.5.0 ; extra == 'docs'
Requires-Dist: furo ==2023.03.27 ; extra == 'docs'
Requires-Dist: nbsphinx ==0.8.12 ; extra == 'docs'
Requires-Dist: rstobj ==1.2.1 ; extra == 'docs'
Requires-Dist: pygments ==2.15.1 ; extra == 'docs'
Requires-Dist: ipython ==8.10.0 ; extra == 'docs'
Requires-Dist: docfly ==2.0.1 ; extra == 'docs'
Provides-Extra: tests
Requires-Dist: pytest ; extra == 'tests'
Requires-Dist: pytest-cov ; extra == 'tests'
Requires-Dist: boto3 ; extra == 'tests'
Requires-Dist: moto ; extra == 'tests'
Requires-Dist: boto-session-manager ; extra == 'tests'
